finpredict/__init__.py
finpredict/lib.py
finpredict-0.0.20.dist-info/LICENSE
finpredict-0.0.20.dist-info/METADATA
finpredict-0.0.20.dist-info/WHEEL
finpredict-0.0.20.dist-info/top_level.txt
finpredict-0.0.20.dist-info/RECORD
