Metadata-Version: 2.1
Name: finpredict
Version: 0.0.20
Summary: Finance tools module
Home-page: https://github.com/omers/finpredict
Author: Omer Segev
Project-URL: Bug Tracker, https://github.com/omers/finpredict/issues
Classifier: Programming Language :: Python :: 3
Classifier: License :: OSI Approved :: MIT License
Classifier: Operating System :: OS Independent
Classifier: Development Status :: 4 - Beta
Requires-Python: >=3.8
License-File: LICENSE
Requires-Dist: pandas (==1.5.1)
Requires-Dist: pandas-datareader (==0.10.0)
Requires-Dist: numpy (==1.23.4)
Requires-Dist: yfinance (==0.1.74)
